pyg600/__init__.py
pyg600/__main__.py
pyg600/config.py
pyg600/constants.py
pyg600/default.yaml
pyg600/pyg600.py
pyg600-1.2.0.dist-info/LICENSE
pyg600-1.2.0.dist-info/METADATA
pyg600-1.2.0.dist-info/WHEEL
pyg600-1.2.0.dist-info/entry_points.txt
pyg600-1.2.0.dist-info/top_level.txt
pyg600-1.2.0.dist-info/RECORD
