Metadata-Version: 2.1
Name: pyg600
Version: 1.2.0
Summary: Utility program for binding actions to keys on the Logitech G600 gaming mouse
Home-page: https://github.com/j-waters/pyg600
Author: James Waters
Author-email: james@jcwaters.co.uk
License: UNKNOWN
Platform: UNKNOWN
Requires-Python: >=3.7
License-File: LICENSE
Requires-Dist: pymacropad
Requires-Dist: Click
